Metadata-Version: 1.0
Name: autodocumentation
Version: 0.0.6
Summary: Some logging helpers: Context, key-value rendering, etc.
Home-page: UNKNOWN
Author: Stas Kaledin
Author-email: staskaledin@gmail.com
License: UNKNOWN
Platform: UNKNOWN
